django_ml_markdown-0.1.0.dist-info/DESCRIPTION.rst
django_ml_markdown-0.1.0.dist-info/METADATA
django_ml_markdown-0.1.0.dist-info/RECORD
django_ml_markdown-0.1.0.dist-info/WHEEL
django_ml_markdown-0.1.0.dist-info/metadata.json
django_ml_markdown-0.1.0.dist-info/top_level.txt
ml_markdown/__init__.py
ml_markdown/apps.py
ml_markdown/test_settings.py
ml_markdown/templatetags/__init__.py
ml_markdown/templatetags/ml_markdown.py
ml_markdown/utils/__init__.py
ml_markdown/utils/default_renderer.py
