Metadata-Version: 2.0
Name: django-ml-markdown
Version: 0.1.0
Summary: A django app that parse markdown to html
Home-page: https://github.com/maxlothaire/django-ml_markdown
Author: Max Lothaire
Author-email: maxlothaire@gmail.com
License: BSD
Keywords: django markdown ml_markdown
Platform: UNKNOWN
Classifier: Development Status :: 3 - Alpha
Classifier: License :: OSI Approved :: BSD License
Classifier: Intended Audience :: Developers
Classifier: Framework :: Django
Classifier: Framework :: Django :: 1.8
Classifier: Framework :: Django :: 1.10
Classifier: Programming Language :: Python :: 2
Classifier: Programming Language :: Python :: 2.6
Classifier: Programming Language :: Python :: 2.7
Classifier: Programming Language :: Python :: 3
Classifier: Programming Language :: Python :: 3.3
Classifier: Programming Language :: Python :: 3.4
Classifier: Programming Language :: Python :: 3.5
Requires-Dist: bleach
Requires-Dist: misaka
Requires-Dist: pygments
